[
    {
        "placement": 1,
        "participant_name": "SK Gaming",
        "roster_id": "9fc25444-d7d8-11ee-98d0-0242ac190002",
        "points": 117
    },
    {
        "placement": 2,
        "participant_name": "HMBLE",
        "roster_id": "ad1e8314-d801-11ee-904d-0242c0a81003",
        "points": 87
    },
    {
        "placement": 3,
        "participant_name": "Oceanus Gaming",
        "roster_id": "2834320a-d7c2-11ee-98b0-0242ac190002",
        "points": 68
    },
    {
        "placement": 4,
        "participant_name": "BC* Gaming",
        "roster_id": "8efeaa28-d8b3-11ee-a8ba-0242ac130003",
        "points": 67
    },
    {
        "placement": 7,
        "participant_name": "Reply Totem",
        "roster_id": "a25ed5dc-d7ed-11ee-8dbe-0242ac190002",
        "points": 53
    },
    {
        "placement": 8,
        "participant_name": "FUT Esports",
        "roster_id": "79dc464e-d8ab-11ee-830f-0242ac190002",
        "points": 52
    },
    {
        "placement": 12,
        "participant_name": "F/A db",
        "roster_id": "bd309552-d7c6-11ee-bf36-0242ac190002",
        "points": 15
    },
    {
        "placement": 13,
        "participant_name": "F/A Cute Kitties",
        "roster_id": "72c85a6a-d80f-11ee-b7b6-0242ac130003",
        "points": 14
    },
    {
        "placement": 14,
        "participant_name": "eGirls",
        "roster_id": "f9e54516-dd7e-11ee-a065-0242ac140002",
        "points": 14
    },
    {
        "placement": 15,
        "participant_name": "F/A ris",
        "roster_id": "052b6f46-dbad-11ee-b4e8-0242ac190002",
        "points": 14
    },
    {
        "placement": 16,
        "participant_name": "Millesime BS",
        "roster_id": "dabe93fe-d7f7-11ee-9ba4-0242c0a81003",
        "points": 14
    },
    {
        "placement": 16,
        "participant_name": "F/A Diff",
        "roster_id": "849d4ee8-dbc6-11ee-80b8-0242ac130003",
        "points": 14
    },
    {
        "placement": 18,
        "participant_name": "AO Instinct",
        "roster_id": "2f3228c0-d95f-11ee-9d24-0242ac190002",
        "points": 13
    },
    {
        "placement": 28,
        "participant_name": "SD_Family",
        "roster_id": "e08aff6a-d7e4-11ee-a74b-0242ac190002",
        "points": 12
    },
    {
        "placement": 30,
        "participant_name": "SJJ",
        "roster_id": "2b9f236e-d9a2-11ee-a1c0-0242ac130003",
        "points": 12
    },
    {
        "placement": 37,
        "participant_name": "Eclipsar School",
        "roster_id": "40eb6008-d7cb-11ee-bc95-0242c0a81002",
        "points": 10
    },
    {
        "placement": 49,
        "participant_name": "SG",
        "roster_id": "ac70fcca-d825-11ee-9518-0242ac130003",
        "points": 10
    },
    {
        "placement": 50,
        "participant_name": "Veni Vidi Vici",
        "roster_id": "065deebe-d7b8-11ee-9736-0242ac190002",
        "points": 10
    },
    {
        "placement": 53,
        "participant_name": "Chickens Squad",
        "roster_id": "9fd87a52-d99b-11ee-9509-0242c0a81003",
        "points": 10
    },
    {
        "placement": 60,
        "participant_name": "Courage One",
        "roster_id": "4521305c-d7ae-11ee-b8b6-0242c0a81002",
        "points": 9
    },
    {
        "placement": 67,
        "participant_name": "葛",
        "roster_id": "84d25c18-d956-11ee-b0bf-0242c0a81003",
        "points": 9
    },
    {
        "placement": 72,
        "participant_name": "GG eSports",
        "roster_id": "62cfbd56-d7fb-11ee-8ac9-0242ac130003",
        "points": 9
    },
    {
        "placement": 73,
        "participant_name": "I Sudati",
        "roster_id": "f5cccb8e-dd60-11ee-992b-0242c0a81003",
        "points": 9
    },
    {
        "placement": 78,
        "participant_name": "No Mans Land",
        "roster_id": "12c74d4c-d8be-11ee-8362-0242ac130003",
        "points": 8
    },
    {
        "placement": 82,
        "participant_name": "JoTopiX",
        "roster_id": "3fc0e530-d9a2-11ee-97d1-0242ac190002",
        "points": 8
    },
    {
        "placement": 94,
        "participant_name": "PGS`eSportS",
        "roster_id": "2075f3ae-d8cc-11ee-abf0-0242ac190002",
        "points": 8
    },
    {
        "placement": 96,
        "participant_name": "CASUALS",
        "roster_id": "255aa0e4-da35-11ee-97d4-0242ac190002",
        "points": 8
    },
    {
        "placement": 99,
        "participant_name": "Sulky Monkey",
        "roster_id": "b182f636-d80d-11ee-9e0d-0242ac130003",
        "points": 8
    },
    {
        "placement": 101,
        "participant_name": "WhiteB",
        "roster_id": "8bcfc582-d7bc-11ee-ace0-0242ac190002",
        "points": 8
    },
    {
        "placement": 114,
        "participant_name": "Black Evolution",
        "roster_id": "5706a364-d7eb-11ee-ab0b-0242ac130003",
        "points": 7
    },
    {
        "placement": 122,
        "participant_name": "Mystic Lancers",
        "roster_id": "7bc32fa6-d7e1-11ee-9804-0242c0a81002",
        "points": 7
    },
    {
        "placement": 123,
        "participant_name": "KNF TEAM",
        "roster_id": "ca951370-d7c7-11ee-87c9-0242ac130003",
        "points": 7
    },
    {
        "placement": 124,
        "participant_name": "ADA | E-sport",
        "roster_id": "9fab1202-d7e7-11ee-bc1a-0242ac190002",
        "points": 7
    },
    {
        "placement": 124,
        "participant_name": "KnaxOpas",
        "roster_id": "c37a9eda-d7e4-11ee-b631-0242ac190002",
        "points": 7
    },
    {
        "placement": 126,
        "participant_name": "CumBusters",
        "roster_id": "b0a203c8-d81d-11ee-8ede-0242ac130003",
        "points": 7
    },
    {
        "placement": 127,
        "participant_name": "M8",
        "roster_id": "fa3ad126-d80f-11ee-b760-0242c0a81003",
        "points": 7
    },
    {
        "placement": 128,
        "participant_name": "F/A Provocation",
        "roster_id": "f7bf2ff0-dcce-11ee-8cbd-0242c0a81003",
        "points": 7
    },
    {
        "placement": 129,
        "participant_name": "MESSI",
        "roster_id": "8e0f1c1c-dc8a-11ee-b7a8-0242ac130003",
        "points": 7
    },
    {
        "placement": 130,
        "participant_name": "MOONLY",
        "roster_id": "e30b6e00-d81b-11ee-a160-0242ac130003",
        "points": 7
    },
    {
        "placement": 133,
        "participant_name": "SSL",
        "roster_id": "eac63b74-d812-11ee-93e1-0242c0a81003",
        "points": 7
    },
    {
        "placement": 135,
        "participant_name": "Yarbzone",
        "roster_id": "e4f6c4f6-d7d2-11ee-a7c8-0242ac190002",
        "points": 6
    },
    {
        "placement": 137,
        "participant_name": "ELITES",
        "roster_id": "2f22257e-d9a5-11ee-9c54-0242ac190002",
        "points": 6
    },
    {
        "placement": 139,
        "participant_name": "Petrellos",
        "roster_id": "90856b62-d948-11ee-9bbd-0242ac190002",
        "points": 6
    },
    {
        "placement": 140,
        "participant_name": "3 inconnus",
        "roster_id": "8dbe98aa-da64-11ee-8246-0242ac130003",
        "points": 6
    },
    {
        "placement": 143,
        "participant_name": "Shock",
        "roster_id": "b1f452e6-d7e9-11ee-b519-0242ac190002",
        "points": 6
    },
    {
        "placement": 144,
        "participant_name": "AAA",
        "roster_id": "3d377eb6-d888-11ee-96bf-0242c0a81003",
        "points": 6
    },
    {
        "placement": 145,
        "participant_name": "Stoned Brawlerzz",
        "roster_id": "1d036fb0-d91e-11ee-acb5-0242ac190002",
        "points": 6
    },
    {
        "placement": 146,
        "participant_name": "Rising Phoenix",
        "roster_id": "77e7145a-d846-11ee-974d-0242ac190002",
        "points": 6
    },
    {
        "placement": 147,
        "participant_name": "TM | 120",
        "roster_id": "935fe362-d7ea-11ee-8042-0242ac190002",
        "points": 6
    },
    {
        "placement": 148,
        "participant_name": "gogo prime",
        "roster_id": "0edf1ac4-d806-11ee-8561-0242c0a81003",
        "points": 6
    },
    {
        "placement": 149,
        "participant_name": "Omega Team",
        "roster_id": "83fb8e50-d7de-11ee-8ede-0242ac130003",
        "points": 6
    },
    {
        "placement": 150,
        "participant_name": "FERIANTES CLAPPED U",
        "roster_id": "1cb32e58-d827-11ee-8d68-0242c0a81003",
        "points": 6
    },
    {
        "placement": 151,
        "participant_name": "EX e-sport",
        "roster_id": "c71d2744-d9a4-11ee-bd7e-0242ac130003",
        "points": 6
    },
    {
        "placement": 152,
        "participant_name": "Stefeti",
        "roster_id": "777d01c2-d7d4-11ee-8daf-0242c0a81002",
        "points": 6
    },
    {
        "placement": 153,
        "participant_name": "RobinDaHood",
        "roster_id": "a7e435d2-da4b-11ee-b5dc-0242c0a81003",
        "points": 6
    },
    {
        "placement": 154,
        "participant_name": "VSV GAMING",
        "roster_id": "6c85d62a-d899-11ee-8795-0242ac130003",
        "points": 6
    },
    {
        "placement": 155,
        "participant_name": "Pydrawak",
        "roster_id": "05d8f294-d971-11ee-92c6-0242ac190002",
        "points": 6
    },
    {
        "placement": 156,
        "participant_name": "VSY",
        "roster_id": "049b2e76-d811-11ee-88da-0242c0a81003",
        "points": 6
    },
    {
        "placement": 157,
        "participant_name": "BaWoWna",
        "roster_id": "3436c918-d96c-11ee-a512-0242c0a81003",
        "points": 6
    },
    {
        "placement": 158,
        "participant_name": "Welwa",
        "roster_id": "6ea01054-d968-11ee-a020-0242ac190002",
        "points": 6
    },
    {
        "placement": 159,
        "participant_name": "Team DB",
        "roster_id": "00906660-d876-11ee-a22c-0242ac130003",
        "points": 6
    },
    {
        "placement": 160,
        "participant_name": "FULGENCIO GANG",
        "roster_id": "8e5144d8-d7c2-11ee-a95d-0242ac190002",
        "points": 6
    },
    {
        "placement": 161,
        "participant_name": "Brawl Papas",
        "roster_id": "8a53cfbc-dd8b-11ee-88f2-0242ac140002",
        "points": 6
    },
    {
        "placement": 162,
        "participant_name": "morenitos",
        "roster_id": "dfc92668-d98f-11ee-ab9e-0242ac130003",
        "points": 6
    },
    {
        "placement": 163,
        "participant_name": "MGTLOSSOSIS",
        "roster_id": "fe0e1218-d800-11ee-b6b0-0242ac190002",
        "points": 6
    },
    {
        "placement": 164,
        "participant_name": "17",
        "roster_id": "6721bba4-d7fe-11ee-882b-0242ac190002",
        "points": 6
    },
    {
        "placement": 165,
        "participant_name": "High Quality",
        "roster_id": "2802cde6-d8da-11ee-b11f-0242c0a81003",
        "points": 6
    },
    {
        "placement": 166,
        "participant_name": "Broke Boys",
        "roster_id": "07dfe1bc-dcb2-11ee-8a1c-0242c0a81003",
        "points": 6
    },
    {
        "placement": 167,
        "participant_name": "Fast Fights",
        "roster_id": "336d414c-d89a-11ee-8270-0242ac130003",
        "points": 6
    },
    {
        "placement": 167,
        "participant_name": "",
        "roster_id": "720e0086-d97f-11ee-9069-0242ac190002",
        "points": 6
    },
    {
        "placement": 169,
        "participant_name": "Finanzamt",
        "roster_id": "d7e0e1aa-d888-11ee-8e39-0242c0a81003",
        "points": 6
    },
    {
        "placement": 169,
        "participant_name": "WTM",
        "roster_id": "373e3cf4-d7dc-11ee-ae89-0242c0a81002",
        "points": 6
    },
    {
        "placement": 169,
        "participant_name": "MVI",
        "roster_id": "436e0aa0-d970-11ee-afb2-0242ac190002",
        "points": 6
    },
    {
        "placement": 169,
        "participant_name": "PSA | BS",
        "roster_id": "92707a50-da12-11ee-9d6d-0242ac190002",
        "points": 6
    },
    {
        "placement": 173,
        "participant_name": "DRG",
        "roster_id": "11f35ac0-d99d-11ee-ac9f-0242ac130003",
        "points": 6
    },
    {
        "placement": 173,
        "participant_name": "★FIZ_esport★",
        "roster_id": "bd672d2a-d94b-11ee-b242-0242ac190002",
        "points": 6
    },
    {
        "placement": 173,
        "participant_name": "Fear",
        "roster_id": "8e390b06-d7af-11ee-9644-0242ac130003",
        "points": 6
    },
    {
        "placement": 176,
        "participant_name": "ALPHA",
        "roster_id": "233925f2-d88b-11ee-b096-0242c0a81003",
        "points": 6
    },
    {
        "placement": 176,
        "participant_name": "teamschwamme",
        "roster_id": "5c2600ca-d961-11ee-9e19-0242ac190002",
        "points": 6
    },
    {
        "placement": 176,
        "participant_name": "Fc Kuh",
        "roster_id": "7c726480-d8d1-11ee-b739-0242ac190002",
        "points": 6
    },
    {
        "placement": 176,
        "participant_name": "ADR",
        "roster_id": "50ef6e0c-dd8b-11ee-9f3f-0242ac140002",
        "points": 6
    },
    {
        "placement": 176,
        "participant_name": "EAN",
        "roster_id": "abc8ba48-d8dd-11ee-a4f7-0242c0a81003",
        "points": 6
    },
    {
        "placement": 176,
        "participant_name": "Pacenici za mindzu",
        "roster_id": "38bd5254-dc14-11ee-9d11-0242c0a81003",
        "points": 6
    },
    {
        "placement": 182,
        "participant_name": "Banditen",
        "roster_id": "004b3cbc-d7f8-11ee-b796-0242ac190002",
        "points": 6
    },
    {
        "placement": 183,
        "participant_name": "LEGIN",
        "roster_id": "b870a410-d88b-11ee-a120-0242ac130003",
        "points": 6
    },
    {
        "placement": 184,
        "participant_name": "BDR SOCIETY",
        "roster_id": "a4df7aa2-d967-11ee-8179-0242ac130003",
        "points": 6
    },
    {
        "placement": 185,
        "participant_name": "Gae House",
        "roster_id": "99a61176-d8ab-11ee-8cad-0242ac190002",
        "points": 6
    },
    {
        "placement": 186,
        "participant_name": "RKK | Gaming EU",
        "roster_id": "c96614b4-d7f3-11ee-b447-0242ac190002",
        "points": 6
    },
    {
        "placement": 187,
        "participant_name": "Pasta Al Sugo ES",
        "roster_id": "936477be-d976-11ee-bfe8-0242ac130003",
        "points": 6
    },
    {
        "placement": 188,
        "participant_name": "Head Dogs Gaming",
        "roster_id": "8d92c642-d7f0-11ee-8eba-0242ac190002",
        "points": 6
    },
    {
        "placement": 189,
        "participant_name": "Emberger",
        "roster_id": "c6a4c1dc-da03-11ee-a0e6-0242c0a81003",
        "points": 6
    },
    {
        "placement": 190,
        "participant_name": "La team SD",
        "roster_id": "6dd6c866-d8be-11ee-a401-0242ac190002",
        "points": 6
    },
    {
        "placement": 190,
        "participant_name": "NitroKillerS",
        "roster_id": "585118e8-d972-11ee-ae36-0242c0a81003",
        "points": 6
    },
    {
        "placement": 190,
        "participant_name": "Hagener ESPORTS",
        "roster_id": "5ef64016-d7d2-11ee-a351-0242c0a81002",
        "points": 6
    },
    {
        "placement": 190,
        "participant_name": "Trivial gaming",
        "roster_id": "5ea20f78-d8a9-11ee-9019-0242c0a81003",
        "points": 6
    },
    {
        "placement": 190,
        "participant_name": "Brawl Hub",
        "roster_id": "68492dc0-d7e3-11ee-b311-0242ac190002",
        "points": 6
    },
    {
        "placement": 195,
        "participant_name": "LRT|LaRilletteTeam",
        "roster_id": "64819d90-d7dd-11ee-a09d-0242ac190002",
        "points": 6
    },
    {
        "placement": 196,
        "participant_name": "Last Life",
        "roster_id": "2169acec-d999-11ee-a47a-0242ac130003",
        "points": 6
    },
    {
        "placement": 197,
        "participant_name": "SMILEE",
        "roster_id": "5e6705ba-d825-11ee-8530-0242ac190002",
        "points": 6
    },
    {
        "placement": 198,
        "participant_name": "PRSKACI",
        "roster_id": "92740a9a-d8a4-11ee-b32b-0242c0a81003",
        "points": 6
    },
    {
        "placement": 202,
        "participant_name": "LosToreros",
        "roster_id": "660b3a40-d896-11ee-a056-0242ac190002",
        "points": 6
    },
    {
        "placement": 203,
        "participant_name": "Noble Diamond Esport",
        "roster_id": "9f288ae2-d88e-11ee-80b4-0242ac190002",
        "points": 6
    },
    {
        "placement": 204,
        "participant_name": "SPIRIT",
        "roster_id": "71b59bb0-d963-11ee-9f68-0242c0a81003",
        "points": 5
    },
    {
        "placement": 205,
        "participant_name": "TKD",
        "roster_id": "b49d8a0a-d959-11ee-936a-0242ac190002",
        "points": 5
    },
    {
        "placement": 206,
        "participant_name": "ClutchPojkarna",
        "roster_id": "51142ebc-da62-11ee-a00f-0242c0a81003",
        "points": 5
    },
    {
        "placement": 207,
        "participant_name": "Team|Laughing coffin",
        "roster_id": "01f1687c-d7e2-11ee-a96c-0242ac130003",
        "points": 5
    },
    {
        "placement": 208,
        "participant_name": "EL-STARS",
        "roster_id": "2de0a48a-d7e6-11ee-a91f-0242ac130003",
        "points": 5
    },
    {
        "placement": 209,
        "participant_name": "BERRIZ BS",
        "roster_id": "e7fa777a-d8b7-11ee-b971-0242c0a81003",
        "points": 5
    },
    {
        "placement": 210,
        "participant_name": "Om",
        "roster_id": "bfef80da-d7b9-11ee-84e9-0242ac130003",
        "points": 5
    },
    {
        "placement": 211,
        "participant_name": "蝎 校校校校",
        "roster_id": "b6fd98e8-d8ce-11ee-9e7c-0242ac190002",
        "points": 5
    },
    {
        "placement": 212,
        "participant_name": "GSP 1.0",
        "roster_id": "a73a09e0-d7b2-11ee-bf83-0242ac130003",
        "points": 5
    },
    {
        "placement": 213,
        "participant_name": "'/N@",
        "roster_id": "bef0bf4a-d8d2-11ee-9d85-0242ac130003",
        "points": 5
    },
    {
        "placement": 213,
        "participant_name": "Sanfer Kings",
        "roster_id": "53190556-d7f7-11ee-84a9-0242c0a81003",
        "points": 5
    },
    {
        "placement": 215,
        "participant_name": "Team_SystM",
        "roster_id": "9cd515ba-d82c-11ee-8251-0242ac190002",
        "points": 5
    },
    {
        "placement": 216,
        "participant_name": "Zob E-Sport",
        "roster_id": "5a32d700-d87d-11ee-837f-0242c0a81003",
        "points": 5
    },
    {
        "placement": 216,
        "participant_name": "{HEMALA}",
        "roster_id": "32fc70d0-d7ef-11ee-92f7-0242c0a81003",
        "points": 5
    },
    {
        "placement": 216,
        "participant_name": "Mystic Angels(bjd)",
        "roster_id": "9c430b80-d7f9-11ee-8c51-0242c0a81003",
        "points": 5
    },
    {
        "placement": 216,
        "participant_name": "Only Gaming",
        "roster_id": "2dd7e2e0-d7c4-11ee-a339-0242c0a81002",
        "points": 5
    },
    {
        "placement": 216,
        "participant_name": "Aura",
        "roster_id": "b7fa81c4-d9f6-11ee-83db-0242c0a81003",
        "points": 5
    },
    {
        "placement": 216,
        "participant_name": "BlueSkorpion",
        "roster_id": "28f4b720-dda1-11ee-a91f-0242ac190002",
        "points": 5
    },
    {
        "placement": 216,
        "participant_name": "STM|gaming",
        "roster_id": "af7a8e2c-d7d5-11ee-942a-0242ac190002",
        "points": 5
    },
    {
        "placement": 223,
        "participant_name": "Coli",
        "roster_id": "4c9c31a4-d9a4-11ee-8b7b-0242ac130003",
        "points": 5
    },
    {
        "placement": 224,
        "participant_name": "Corrupted Souls",
        "roster_id": "972126ec-d7ee-11ee-b6cb-0242ac190002",
        "points": 5
    },
    {
        "placement": 224,
        "participant_name": "Macan-ESP",
        "roster_id": "ecb20b64-d8c8-11ee-b234-0242ac130003",
        "points": 5
    },
    {
        "placement": 226,
        "participant_name": "JAI ESPORTS",
        "roster_id": "76b8ee48-d808-11ee-be38-0242ac130003",
        "points": 5
    },
    {
        "placement": 227,
        "participant_name": "DTL",
        "roster_id": "2913dabc-d881-11ee-bfbb-0242ac190002",
        "points": 5
    },
    {
        "placement": 228,
        "participant_name": "TS|SUISSE",
        "roster_id": "f39af4a4-d805-11ee-9eca-0242ac190002",
        "points": 5
    },
    {
        "placement": 229,
        "participant_name": "Tutel Team Three",
        "roster_id": "d8da2a9c-dbfa-11ee-b738-0242ac190002",
        "points": 5
    },
    {
        "placement": 230,
        "participant_name": "THE GOATS",
        "roster_id": "f50636c2-d865-11ee-9be8-0242c0a81003",
        "points": 5
    },
    {
        "placement": 231,
        "participant_name": "Die keneks",
        "roster_id": "3e5108ec-d8a3-11ee-81fc-0242ac130003",
        "points": 5
    },
    {
        "placement": 232,
        "participant_name": "Team PAD",
        "roster_id": "ff0736a2-d8de-11ee-b1c0-0242c0a81003",
        "points": 5
    },
    {
        "placement": 233,
        "participant_name": "XXX",
        "roster_id": "818b8ef6-d7cd-11ee-b027-0242c0a81002",
        "points": 5
    },
    {
        "placement": 234,
        "participant_name": "The Mulldrifters",
        "roster_id": "255c6b66-da6e-11ee-984d-0242c0a81003",
        "points": 5
    },
    {
        "placement": 235,
        "participant_name": "BOOM Esports",
        "roster_id": "2040e0fc-d8c1-11ee-844f-0242c0a81003",
        "points": 5
    },
    {
        "placement": 236,
        "participant_name": "GERARDITO JR",
        "roster_id": "664a0a8c-d7e1-11ee-a643-0242c0a81002",
        "points": 5
    },
    {
        "placement": 236,
        "participant_name": "Los cachiporros",
        "roster_id": "0cbdd4ba-d7d4-11ee-8e36-0242ac190002",
        "points": 5
    },
    {
        "placement": 236,
        "participant_name": "Gobsslayer",
        "roster_id": "ac3699dc-dad1-11ee-b14a-0242c0a81003",
        "points": 5
    },
    {
        "placement": 239,
        "participant_name": "AVZA",
        "roster_id": "8e1b8b3c-d9ec-11ee-b2b3-0242ac130003",
        "points": 5
    },
    {
        "placement": 243,
        "participant_name": "Stigma Ember",
        "roster_id": "2c55f2ee-db08-11ee-828e-0242ac190002",
        "points": 5
    },
    {
        "placement": 248,
        "participant_name": "Xperia",
        "roster_id": "b9e5ffea-f4f9-11ee-80a3-0242ac130003",
        "points": 4
    },
    {
        "placement": 248,
        "participant_name": "Ramen | eSports",
        "roster_id": "0b845580-d7f5-11ee-9b53-0242ac190002",
        "points": 4
    },
    {
        "placement": 248,
        "participant_name": "WW Team",
        "roster_id": "129ab7e2-f361-11ee-a68a-0242ac130003",
        "points": 4
    },
    {
        "placement": 248,
        "participant_name": "BDB-33",
        "roster_id": "3b8e2ef2-d905-11ee-b397-0242ac130003",
        "points": 4
    },
    {
        "placement": 248,
        "participant_name": "KRAKENWAKEN",
        "roster_id": "f36d50d0-f646-11ee-884e-0242ac130003",
        "points": 4
    },
    {
        "placement": 248,
        "participant_name": "Old gang",
        "roster_id": "90fcceaa-f360-11ee-9b17-0242ac130003",
        "points": 4
    },
    {
        "placement": 248,
        "participant_name": "iTanfi",
        "roster_id": "103574d6-f386-11ee-9295-0242ac130003",
        "points": 4
    },
    {
        "placement": 248,
        "participant_name": "TSM  Fusion",
        "roster_id": "dc3d8dee-f42a-11ee-9301-0242ac130003",
        "points": 4
    },
    {
        "placement": 248,
        "participant_name": "QUEQUETTE-SPORT",
        "roster_id": "94426790-f39d-11ee-bce8-0242ac130003",
        "points": 4
    },
    {
        "placement": 248,
        "participant_name": "Unkown Talents",
        "roster_id": "76618f22-f338-11ee-923c-0242ac130002",
        "points": 4
    },
    {
        "placement": 248,
        "participant_name": "Washed",
        "roster_id": "5c1c70f8-f641-11ee-aa9e-0242ac130003",
        "points": 4
    },
    {
        "placement": 248,
        "participant_name": "Ceci Brawl",
        "roster_id": "064b9250-f4f0-11ee-9d9c-0242ac130003",
        "points": 4
    },
    {
        "placement": 248,
        "participant_name": "KOL gaming",
        "roster_id": "e5ba0eb8-f4ef-11ee-8ba1-0242ac130003",
        "points": 4
    },
    {
        "placement": 248,
        "participant_name": "Jansa eSports",
        "roster_id": "eae2a108-f372-11ee-a24d-0242ac130003",
        "points": 4
    },
    {
        "placement": 248,
        "participant_name": "The Blades",
        "roster_id": "ee358870-f372-11ee-ba12-0242ac130003",
        "points": 4
    },
    {
        "placement": 248,
        "participant_name": "RHE ESPORTS",
        "roster_id": "96cc82b2-d8b2-11ee-bf7b-0242ac190002",
        "points": 4
    },
    {
        "placement": 248,
        "participant_name": "Kaniuka",
        "roster_id": "654da5c6-f352-11ee-9eba-0242ac130003",
        "points": 4
    },
    {
        "placement": 248,
        "participant_name": "Souly",
        "roster_id": "6e3e70a6-d7ec-11ee-81fe-0242ac190002",
        "points": 4
    },
    {
        "placement": 248,
        "participant_name": "Star Gaming Lords",
        "roster_id": "005169fc-f382-11ee-bd04-0242ac130003",
        "points": 4
    },
    {
        "placement": 248,
        "participant_name": "LAVOVI",
        "roster_id": "fbf73d76-f36a-11ee-965e-0242ac130003",
        "points": 4
    },
    {
        "placement": 248,
        "participant_name": "AUTISMUS PRIME",
        "roster_id": "005a0498-f36b-11ee-a4e4-0242ac130003",
        "points": 4
    },
    {
        "placement": 248,
        "participant_name": "Flop FC",
        "roster_id": "20935410-f660-11ee-926f-0242ac130003",
        "points": 4
    },
    {
        "placement": 248,
        "participant_name": "Arab Nation",
        "roster_id": "77860786-f476-11ee-841e-0242ac130003",
        "points": 4
    },
    {
        "placement": 248,
        "participant_name": "MARRECOS",
        "roster_id": "fe32977a-db41-11ee-9fb6-0242c0a81003",
        "points": 4
    },
    {
        "placement": 248,
        "participant_name": "OGP",
        "roster_id": "688cc9fa-f916-11ee-872d-0242ac130003",
        "points": 4
    },
    {
        "placement": 248,
        "participant_name": "ND Gaming",
        "roster_id": "855f1680-f36e-11ee-9887-0242ac130003",
        "points": 4
    },
    {
        "placement": 248,
        "participant_name": "CSP",
        "roster_id": "3817361e-f503-11ee-986b-0242ac130003",
        "points": 4
    },
    {
        "placement": 275,
        "participant_name": "Violence Players",
        "roster_id": "5050efe4-f37e-11ee-88e0-0242ac130003",
        "points": 4
    },
    {
        "placement": 275,
        "participant_name": "FF",
        "roster_id": "b9fd2b8e-d8e3-11ee-8b3d-0242c0a81003",
        "points": 4
    },
    {
        "placement": 275,
        "participant_name": "Just Magic",
        "roster_id": "930ed770-dcc6-11ee-a235-0242ac130003",
        "points": 4
    },
    {
        "placement": 275,
        "participant_name": "STS",
        "roster_id": "43bd3916-f457-11ee-949e-0242ac130003",
        "points": 4
    },
    {
        "placement": 275,
        "participant_name": "F/A Grinders",
        "roster_id": "b04accd6-f5e4-11ee-8757-0242ac130003",
        "points": 4
    },
    {
        "placement": 275,
        "participant_name": "EWA",
        "roster_id": "6a714960-da14-11ee-89b3-0242ac130003",
        "points": 4
    },
    {
        "placement": 275,
        "participant_name": "肖校孝",
        "roster_id": "b881b0c4-d7ec-11ee-93ad-0242c0a81003",
        "points": 4
    },
    {
        "placement": 275,
        "participant_name": "Die Absahner",
        "roster_id": "4acfc4e0-f389-11ee-9c2f-0242ac130003",
        "points": 4
    },
    {
        "placement": 275,
        "participant_name": "ESP/ZER",
        "roster_id": "b54d4bc8-f4f9-11ee-a129-0242ac130003",
        "points": 4
    },
    {
        "placement": 275,
        "participant_name": "COSCIOT TEAM",
        "roster_id": "f95a843a-f6f6-11ee-8633-0242ac130003",
        "points": 4
    },
    {
        "placement": 285,
        "participant_name": "Destiny",
        "roster_id": "71753388-f360-11ee-8aeb-0242ac130003",
        "points": 4
    },
    {
        "placement": 285,
        "participant_name": "BG",
        "roster_id": "21addb58-f332-11ee-aed5-0242ac130003",
        "points": 4
    },
    {
        "placement": 285,
        "participant_name": "Mafiosos",
        "roster_id": "37c85384-d7e7-11ee-931b-0242ac190002",
        "points": 4
    },
    {
        "placement": 285,
        "participant_name": "APE PLAY",
        "roster_id": "1b5b8200-f364-11ee-809f-0242ac130003",
        "points": 4
    },
    {
        "placement": 289,
        "participant_name": "gy kumbara",
        "roster_id": "8dc583d8-f399-11ee-af17-0242ac130003",
        "points": 4
    },
    {
        "placement": 290,
        "participant_name": "TU | Team Unpossible",
        "roster_id": "3ce2085e-db3b-11ee-9c59-0242c0a81003",
        "points": 4
    },
    {
        "placement": 291,
        "participant_name": "SOSISKI",
        "roster_id": "05809eb4-d93f-11ee-998c-0242ac130003",
        "points": 4
    },
    {
        "placement": 291,
        "participant_name": "VENOM",
        "roster_id": "8f5216e8-d991-11ee-b8fe-0242ac190002",
        "points": 4
    },
    {
        "placement": 291,
        "participant_name": "Alien Esports",
        "roster_id": "803d8c82-f575-11ee-9f10-0242ac130003",
        "points": 4
    },
    {
        "placement": 291,
        "participant_name": "KaiHasReturned",
        "roster_id": "45024866-f452-11ee-9136-0242ac130003",
        "points": 4
    },
    {
        "placement": 291,
        "participant_name": "Los Primosss",
        "roster_id": "f91df226-f436-11ee-bda3-0242ac130003",
        "points": 4
    },
    {
        "placement": 296,
        "participant_name": "Fresh Boys",
        "roster_id": "418470f4-f8eb-11ee-88c1-0242ac130003",
        "points": 4
    },
    {
        "placement": 296,
        "participant_name": "Serbian boys",
        "roster_id": "2e9694ac-f780-11ee-b442-0242ac130003",
        "points": 4
    },
    {
        "placement": 296,
        "participant_name": "FAME",
        "roster_id": "35632282-f6a9-11ee-9b3b-0242ac130003",
        "points": 4
    },
    {
        "placement": 296,
        "participant_name": "Say gex",
        "roster_id": "c914e016-f49b-11ee-806e-0242ac130003",
        "points": 4
    },
    {
        "placement": 296,
        "participant_name": "RKM",
        "roster_id": "185282fc-f503-11ee-b8c4-0242ac130003",
        "points": 4
    },
    {
        "placement": 296,
        "participant_name": "Cro Warriors",
        "roster_id": "5ab99c40-f385-11ee-8cb9-0242ac130003",
        "points": 4
    },
    {
        "placement": 302,
        "participant_name": "For dinti",
        "roster_id": "2dfd1908-d90d-11ee-98c9-0242ac130003",
        "points": 4
    },
    {
        "placement": 302,
        "participant_name": "AST | Apocalyptique",
        "roster_id": "fa896092-f8e5-11ee-9832-0242ac130003",
        "points": 4
    },
    {
        "placement": 304,
        "participant_name": "Furious Monkeys",
        "roster_id": "89322004-f8f0-11ee-b31f-0242ac130003",
        "points": 4
    },
    {
        "placement": 309,
        "participant_name": "Influx",
        "roster_id": "695612f2-d82c-11ee-98e1-0242ac190002",
        "points": 4
    },
    {
        "placement": 316,
        "participant_name": "Team Penguins",
        "roster_id": "cf2f8796-d8a6-11ee-bf2a-0242ac190002",
        "points": 4
    },
    {
        "placement": 319,
        "participant_name": "Get Roasted",
        "roster_id": "de64f158-d930-11ee-b9a1-0242ac190002",
        "points": 4
    },
    {
        "placement": 329,
        "participant_name": "QWaNsee",
        "roster_id": "414b1f3a-d81a-11ee-93ee-0242ac190002",
        "points": 4
    }
]